mindar/__init__.py
mindar/compiler.py
mindar/detector.py
mindar/features.py
mindar/freak.py
mindar/kernels.py
mindar/matcher.py
mindar/tracker.py
mindar/types.py
mindar-0.1.2.dist-info/LICENSE
mindar-0.1.2.dist-info/METADATA
mindar-0.1.2.dist-info/WHEEL
mindar-0.1.2.dist-info/entry_points.txt
mindar-0.1.2.dist-info/RECORD
