Metadata-Version: 2.3
Name: mindar
Version: 0.1.2
Summary: High-performance MindAR implementation for real-time image recognition on edge devices. Developed by FANSEE LAB.
License: MIT
Author: FANSEE LAB
Author-email: info@fansee.com
Maintainer: FANSEE LAB
Maintainer-email: info@fansee.com
Requires-Python: >=3.9,<4.0
Classifier: License :: OSI Approved :: MIT License
Classifier: Programming Language :: Python :: 3
Classifier: Programming Language :: Python :: 3.9
Classifier: Programming Language :: Python :: 3.10
Classifier: Programming Language :: Python :: 3.11
Classifier: Programming Language :: Python :: 3.12
Classifier: Programming Language :: Python :: 3.13
Provides-Extra: dev
Provides-Extra: performance
Requires-Dist: black (>=25.0.0) ; (python_version >= "3.9") and (extra == "dev")
Requires-Dist: isort (>=6.0.0) ; (python_version >= "3.9") and (extra == "dev")
Requires-Dist: msgpack (>=1.0.0)
Requires-Dist: numba (>=0.59.0)
Requires-Dist: numpy (>=1.26.0) ; python_version >= "3.9"
Requires-Dist: opencv-python (>=4.5.0) ; python_version >= "3.9"
Requires-Dist: pytest (>=8.0.0) ; (python_version >= "3.8") and (extra == "dev")
Requires-Dist: pytest-cov (>=6.0.0) ; (python_version >= "3.9") and (extra == "dev")
Project-URL: Documentation, https://github.com/FANSEE-LAB/mind-ar#readme
Project-URL: Repository, https://github.com/FANSEE-LAB/mind-ar
